{

	"projects": {
		"projectsEndPoint":"https:\/\/www.pivotaltracker.com\/services\/v5\/projects",
		"projectByIdEndPoint":"https:\/\/www.pivotaltracker.com\/services\/v5\/projects\/{project_id}",
		"storiesTasksEndPoint":"https:\/\/www.pivotaltracker.com\/services\/v5\/projects\/{project_id}\/stories\/{story_id}\/tasks",
		"storiesTasksByIdEndPoint":"https:\/\/www.pivotaltracker.com\/services\/v5\/projects\/{project_id}\/stories\/{story_id}\/tasks\/{task_id}"
	},

	"me": {
		"meEndPoint":"https://www.pivotaltracker.com/services/v5/me"
	},

	"stories": {
		"storiesEndPoint":"https:\/\/www.pivotaltracker.com/services/v5/projects/{project_id}/stories"
	},

	"story": {
		"storyEndPoint":"https:\/\/www.pivotaltracker.com/services/v5/projects/{project_id}/stories/{story_id}",
		"storyOwnersEndPoint":"https:\/\/www.pivotaltracker.com/services/v5/projects/{project_id}/stories/{story_id}/owners"
	},

	"iteration": {
		"iterationtokenEndPoint" : "https:\/\/www.pivotaltracker.com\/services\/v5\/projects\/{project_id}\/iterations",
		"iterationtokenEndPoint2" : "https:\/\/www.pivotaltracker.com\/services\/v5\/projects\/{project_id}\/iteration_overrides\/{iteration_number}"	
	}

	,"labels": {
		"labelsOfProjectEndPoint":"https:\/\/www.pivotaltracker.com\/services\/v5\/projects\/1447838\/labels?date_format=millis",

		"labelsProjectEndPoint":"https:\/\/www.pivotaltracker.com\/services\/v5\/projects\/{project_id}\/labels",
		"labelsByStoyIdEndPoint":"https:\/\/www.pivotaltracker.com\/services\/v5\/projects\/{project_id}\/stories\/{story_id}\/labels"		
	},
	"label": {
		
		"storiesEndPoint":"https:\/\/www.pivotaltracker.com\/services\/v5\/projects\/{project_id}\/stories",
		"labelByIdProjectIdEndPoint":"https:\/\/www.pivotaltracker.com\/services\/v5\//projects\/{project_id}\/labels\/{label_id}"		
				
	}, 

	"labels": {
		"labelsOfProjectEndPoint":"https:\/\/www.pivotaltracker.com\/services\/v5\/projects\/1447838\/labels?date_format=millis",

		"labelsProjectEndPoint":"https:\/\/www.pivotaltracker.com\/services\/v5\/projects\/{project_id}\/labels",
		"labelsByStoyIdEndPoint":"https:\/\/www.pivotaltracker.com\/services\/v5\/projects\/{project_id}\/stories\/{story_id}\/labels"		
	},
	"label": {
		
		"storiesEndPoint":"https:\/\/www.pivotaltracker.com\/services\/v5\/projects\/{project_id}\/stories",
		"labelByIdProjectIdEndPoint":"https:\/\/www.pivotaltracker.com\/services\/v5\//projects\/{project_id}\/labels\/{label_id}"		
				
	}

}